modelviz/__init__.py
modelviz/confusion_matrix.py
modelviz/deep_learning.py
modelviz/forecast.py
modelviz/histogram.py
modelviz/kfold.py
modelviz/missvals.py
modelviz/model_eval.py
modelviz/pca.py
modelviz/regression.py
modelviz/relationships.py
modelviz/roc.py
modelviz/timeseries.py
modelviz-3.0.1.dist-info/licenses/LICENSE
tests/__init__.py
tests/test_deep_learning.py
tests/test_forecasts.py
tests/test_multi_mod_viz.py
tests/test_pca.py
tests/test_plot_cm.py
tests/test_plot_feature_histograms.py
tests/test_plot_forecast.py
tests/test_plot_kfold_cv.py
tests/test_plot_missing_values_heatmap.py
tests/test_plot_roc_curve_with_threshold.py
tests/test_prob_plot.py
tests/test_regression.py
tests/test_similarity.py
tests/test_timeseries.py
modelviz-3.0.1.dist-info/METADATA
modelviz-3.0.1.dist-info/WHEEL
modelviz-3.0.1.dist-info/top_level.txt
modelviz-3.0.1.dist-info/RECORD
