Metadata-Version: 2.4
Name: modelviz
Version: 3.0.1
Summary: A package for EDA and Sci-Kit Learn visualisations and utilities
Home-page: https://github.com/StatsGary/modelviz
Author: Gary Hutson
Author-email: hutsons-hacks@outlook.com
Classifier: Programming Language :: Python :: 3.9
Classifier: Programming Language :: Python :: 3.10
Classifier: Programming Language :: Python :: 3.11
Classifier: Programming Language :: Python :: 3.12
Classifier: License :: OSI Approved :: MIT License
Classifier: Operating System :: OS Independent
Requires-Python: >=3.9
License-File: LICENSE
Requires-Dist: numpy
Requires-Dist: scikit-learn
Requires-Dist: matplotlib
Requires-Dist: pandas
Requires-Dist: plotly.express
Requires-Dist: seaborn
Requires-Dist: statsmodels
Requires-Dist: scipy
Requires-Dist: prophet
Provides-Extra: dev
Requires-Dist: pytest>=7.0; extra == "dev"
Dynamic: author
Dynamic: author-email
Dynamic: classifier
Dynamic: description
Dynamic: description-content-type
Dynamic: home-page
Dynamic: license-file
Dynamic: provides-extra
Dynamic: requires-dist
Dynamic: requires-python
Dynamic: summary
